{
    "128KGame": true,
    "Name": "Terramex",
    "Options": {
        "ViewConfigs": [
            {
                "Enabled": true,
                "ViewAddress": 37079,
                "ViewAddressBank": 4
            },
            {
                "Enabled": false,
                "ViewAddress": 0,
                "ViewAddressBank": -1
            },
            {
                "Enabled": false,
                "ViewAddress": 0,
                "ViewAddressBank": -1
            },
            {
                "Enabled": false,
                "ViewAddress": 0,
                "ViewAddressBank": -1
            }
        ],
        "WriteSnapshot": false
    },
    "SnapshotFile": "Terramex.z80"
}
